{
  "description": "项目配置文件，详见文档：https://developers.weixin.qq.com/miniprogram/dev/devtools/projectconfig.html",
  "setting": {
    "useCompilerPlugins": [
      "typescript",
      "less"
    ],
    "urlCheck": true,
    "es6": true,
    "enhance": true,
    "postcss": true,
    "preloadBackgroundData": false,
    "minified": true,
    "newFeature": false,
    "coverView": true,
    "nodeModules": true,
    "autoAudits": false,
    "showShadowRootInWxmlPanel": true,
    "scopeDataCheck": false,
    "uglifyFileName": false,
    "checkInvalidKey": true,
    "checkSiteMap": true,
    "uploadWithSourceMap": true,
    "compileHotReLoad": false,
    "lazyloadPlaceholderEnable": false,
    "useMultiFrameRuntime": true,
    "ignoreDevUnusedFiles": false,
    "babelSetting": {
      "ignore": [],
      "disablePlugins": [],
      "outputPath": ""
    },
    "enableEngineNative": false,
    "useIsolateContext": true,
    "userConfirmedBundleSwitch": false,
    "packNpmManually": false,
    "packNpmRelationList": [],
    "minifyWXSS": true,
    "disableUseStrict": false,
    "minifyWXML": true,
    "showES6CompileOption": false,
    "ignoreUploadUnusedFiles": true,
    "useStaticServer": true,
    "condition": false
  },
  "compileType": "miniprogram",
  "simulatorType": "wechat",
  "simulatorPluginLibVersion": {},
  "condition": {
    "miniprogram": {
      "list": [
        {
          "name": "首页入 口",
          "pathName": "pages/home/home",
          "query": "",
          "scene": null
        },
        {
          "name": "示例页-商品分类",
          "pathName": "pages/goods/category/index",
          "query": "",
          "scene": null
        },
        {
          "name": "示例页-个人中心",
          "pathName": "pages/usercenter/index",
          "query": "",
          "scene": null
        },
        {
          "name": "示例页-商品详情",
          "pathName": "pages/goods/details/index",
          "query": "",
          "scene": null
        },
        {
          "name": "示例页-售后详情",
          "pathName": "pages/order/after-service-detail/index",
          "query": "rightsNo=123123423",
          "scene": null
        },
        {
          "name": "示例页-搜索页",
          "pathName": "pages/goods/search/index",
          "query": "",
          "scene": null
        }
      ]
    }
  },
  "editorSetting": {
    "tabIndent": "insertSpaces",
    "tabSize": 2
  },
  "packOptions": {
    "ignore": [],
    "include": []
  },
  "appid": "wxbef31cb0acc4e14c"
}